LICENSE
MANIFEST.in
README.md
scrapy.cfg
setup.cfg
setup.py
os_scrapy_kafka_pipeline/__init__.py
os_scrapy_kafka_pipeline/exporter.py
os_scrapy_kafka_pipeline/items.py
os_scrapy_kafka_pipeline/middlewares.py
os_scrapy_kafka_pipeline/pipelines.py
os_scrapy_kafka_pipeline/producer.py
os_scrapy_kafka_pipeline/serialize.py
os_scrapy_kafka_pipeline/settings.py
os_scrapy_kafka_pipeline/utils.py
os_scrapy_kafka_pipeline.egg-info/PKG-INFO
os_scrapy_kafka_pipeline.egg-info/SOURCES.txt
os_scrapy_kafka_pipeline.egg-info/dependency_links.txt
os_scrapy_kafka_pipeline.egg-info/not-zip-safe
os_scrapy_kafka_pipeline.egg-info/requires.txt
os_scrapy_kafka_pipeline.egg-info/top_level.txt
os_scrapy_kafka_pipeline/spiders/__init__.py
requirements/requirements-lint.txt
requirements/requirements-test.txt
requirements/requirements.txt
tests/__init__.py
tests/test_scrapy_check.py